Metadata-Version: 1.1
Name: ibreakdown
Version: 0.0.1a4
Summary: ibreakdown - model agnostic explanations with interactions
Home-page: https://github.com/jettify/ibreakdown
Author: Nikolay Novik
Author-email: nickolainovik@gmail.com
License: Apache 2
Download-URL: https://pypi.python.org/pypi/ibreakdown
Keywords: ibreakdown,model explanation,xai
Platform: POSIX
Classifier: License :: OSI Approved :: Apache Software License
Classifier: Intended Audience :: Developers
Classifier: Programming Language :: Python :: 3
Classifier: Programming Language :: Python :: 3.6
Classifier: Programming Language :: Python :: 3.7
Classifier: Operating System :: POSIX
Classifier: Development Status :: 2 - Pre-Alpha
